myfunctions_zulyakeldibaeva/__init__.py
myfunctions_zulyakeldibaeva/math.py
myfunctions_zulyakeldibaeva-0.0.5.dist-info/METADATA
myfunctions_zulyakeldibaeva-0.0.5.dist-info/WHEEL
myfunctions_zulyakeldibaeva-0.0.5.dist-info/top_level.txt
myfunctions_zulyakeldibaeva-0.0.5.dist-info/RECORD
