Metadata-Version: 2.1
Name: myfunctions-zulyakeldibaeva
Version: 0.0.5
Summary: A description of your package
Home-page: https://github.com/zulyakeldibaeva
Author: Zulfiia Keldibaeva
Author-email: zulfiiakeldibaeva@gmail.com
License: MIT
Platform: UNKNOWN
Classifier: Programming Language :: Python :: 3
Classifier: License :: OSI Approved :: MIT License
Classifier: Operating System :: OS Independent
Requires-Python: >=3.6
